Workbook

Sheet Ingreso
B2: Encargado | C2: Federico
B3: Fecha | C3: 44007
C5: Horario | E5: Extras
C6: Desde | D6: Hasta | E6: Vestuario | F6: Refrigerio | G6: Personas | I6: RESTA | J6: Final | K6: TOTAL | L6: Extra Luz | N6: Vestuario | O6: Refrigerio
B7: Turno 1 | C7: 0.375 | D7: 0.4375 | E7: Bàsico | F7: Minimo | G7: 10 | I7: =D7-C7 -> 0.0625 | J7: =IF(HOUR(I7)<1,_xlfn.CEILING.MATH(I7,"01:00"),_xlfn.CEILING.MATH(I7,"00:10")) -> 0.0625 | K7: =((HOUR(J7)*'Lista de Precios'!$C$5)+(MINUTE(J7)/10*'Lista de Precios'!$E$5))*G7 -> 1450 | L7: =IF(C7>0.75, ((HOUR(J7)*'Lista de Precios'!$D$5)+(MINUTE(J7)/10*'Lista de Precios'!$F$5))*G7, 0) -> 0 | N7: =IF(E7='Lista de Precios'!$C$6,'Lista de Precios'!$C$7,IF(E7='Lista de Precios'!$D$6,'Lista de Precios'!$D$7,IF(E7='Lista de Precios'!$E$6,'Lista de Precios'!$E$7,IF(E7='Lista de Precios'!$F$6,'Lista de Precios'!$F$7,0))))*G7 -> 300 | O7: =IF(F7='Lista de Precios'!$C$8,'Lista de Precios'!$C$9,IF(F7='Lista de Precios'!$D$8,'Lista de Precios'!$D$9,IF(F7='Lista de Precios'!$E$8,'Lista de Precios'!$E$9,IF(F7='Lista de Precios'!$F$8,'Lista de Precios'!$F$9,IF(F7='Lista de Precios'!$G$8,'Lista de Precios'!$G$9,0)))))*Ingreso!G7 -> 900
B8: Turno 2 | C8: 0.44791667 | D8: 0.49583333 | E8: Confort | F8: Bàsico | G8: 12 | I8: =D8-C8 -> 0.047916667 | J8: =IF(HOUR(I8)<1,_xlfn.CEILING.MATH(I8,"01:00"),_xlfn.CEILING.MATH(I8,"00:10")) -> 0.048611111 | K8: =((HOUR(J8)*'Lista de Precios'!$C$5)+(MINUTE(J8)/10*'Lista de Precios'!$E$5))*G8 -> 1380 | L8: =IF(C8>0.75, ((HOUR(J8)*'Lista de Precios'!$D$5)+(MINUTE(J8)/10*'Lista de Precios'!$F$5))*G8, 0) -> 0 | N8: =IF(E8='Lista de Precios'!$C$6,'Lista de Precios'!$C$7,IF(E8='Lista de Precios'!$D$6,'Lista de Precios'!$D$7,IF(E8='Lista de Precios'!$E$6,'Lista de Precios'!$E$7,IF(E8='Lista de Precios'!$F$6,'Lista de Precios'!$F$7,0))))*G8 -> 720 | O8: =IF(F8='Lista de Precios'!$C$8,'Lista de Precios'!$C$9,IF(F8='Lista de Precios'!$D$8,'Lista de Precios'!$D$9,IF(F8='Lista de Precios'!$E$8,'Lista de Precios'!$E$9,IF(F8='Lista de Precios'!$F$8,'Lista de Precios'!$F$9,IF(F8='Lista de Precios'!$G$8,'Lista de Precios'!$G$9,0)))))*Ingreso!G8 -> 1320
B9: Turno 3 | C9: 0.50069444 | D9: 0.53055556 | E9: No | F9: No | G9: 11 | I9: =D9-C9 -> 0.029861111 | J9: =IF(HOUR(I9)<1,_xlfn.CEILING.MATH(I9,"01:00"),_xlfn.CEILING.MATH(I9,"00:10")) -> 0.041666667 | K9: =((HOUR(J9)*'Lista de Precios'!$C$5)+(MINUTE(J9)/10*'Lista de Precios'!$E$5))*G9 -> 1100 | L9: =IF(C9>0.75, ((HOUR(J9)*'Lista de Precios'!$D$5)+(MINUTE(J9)/10*'Lista de Precios'!$F$5))*G9, 0) -> 0 | N9: =IF(E9='Lista de Precios'!$C$6,'Lista de Precios'!$C$7,IF(E9='Lista de Precios'!$D$6,'Lista de Precios'!$D$7,IF(E9='Lista de Precios'!$E$6,'Lista de Precios'!$E$7,IF(E9='Lista de Precios'!$F$6,'Lista de Precios'!$F$7,0))))*G9 -> 0 | O9: =IF(F9='Lista de Precios'!$C$8,'Lista de Precios'!$C$9,IF(F9='Lista de Precios'!$D$8,'Lista de Precios'!$D$9,IF(F9='Lista de Precios'!$E$8,'Lista de Precios'!$E$9,IF(F9='Lista de Precios'!$F$8,'Lista de Precios'!$F$9,IF(F9='Lista de Precios'!$G$8,'Lista de Precios'!$G$9,0)))))*Ingreso!G9 -> 0
B10: Turno 4 | C10: 0.55555556 | D10: 0.63958333 | E10: Confort | F10: Abundante | G10: 15 | I10: =D10-C10 -> 0.084027778 | J10: =IF(HOUR(I10)<1,_xlfn.CEILING.MATH(I10,"01:00"),_xlfn.CEILING.MATH(I10,"00:10")) -> 0.090277778 | K10: =((HOUR(J10)*'Lista de Precios'!$C$5)+(MINUTE(J10)/10*'Lista de Precios'!$E$5))*G10 -> 3225 | L10: =IF(C10>0.75, ((HOUR(J10)*'Lista de Precios'!$D$5)+(MINUTE(J10)/10*'Lista de Precios'!$F$5))*G10, 0) -> 0 | N10: =IF(E10='Lista de Precios'!$C$6,'Lista de Precios'!$C$7,IF(E10='Lista de Precios'!$D$6,'Lista de Precios'!$D$7,IF(E10='Lista de Precios'!$E$6,'Lista de Precios'!$E$7,IF(E10='Lista de Precios'!$F$6,'Lista de Precios'!$F$7,0))))*G10 -> 900 | O10: =IF(F10='Lista de Precios'!$C$8,'Lista de Precios'!$C$9,IF(F10='Lista de Precios'!$D$8,'Lista de Precios'!$D$9,IF(F10='Lista de Precios'!$E$8,'Lista de Precios'!$E$9,IF(F10='Lista de Precios'!$F$8,'Lista de Precios'!$F$9,IF(F10='Lista de Precios'!$G$8,'Lista de Precios'!$G$9,0)))))*Ingreso!G10 -> 1950
B11: Turno 5 | C11: 0.64583333 | D11: 0.75347222 | E11: Premium | F11: Abundante | G11: 13 | I11: =D11-C11 -> 0.10763889 | J11: =IF(HOUR(I11)<1,_xlfn.CEILING.MATH(I11,"01:00"),_xlfn.CEILING.MATH(I11,"00:10")) -> 0.11111111 | K11: =((HOUR(J11)*'Lista de Precios'!$C$5)+(MINUTE(J11)/10*'Lista de Precios'!$E$5))*G11 -> 3380 | L11: =IF(C11>0.75, ((HOUR(J11)*'Lista de Precios'!$D$5)+(MINUTE(J11)/10*'Lista de Precios'!$F$5))*G11, 0) -> 0 | N11: =IF(E11='Lista de Precios'!$C$6,'Lista de Precios'!$C$7,IF(E11='Lista de Precios'!$D$6,'Lista de Precios'!$D$7,IF(E11='Lista de Precios'!$E$6,'Lista de Precios'!$E$7,IF(E11='Lista de Precios'!$F$6,'Lista de Precios'!$F$7,0))))*G11 -> 1560 | O11: =IF(F11='Lista de Precios'!$C$8,'Lista de Precios'!$C$9,IF(F11='Lista de Precios'!$D$8,'Lista de Precios'!$D$9,IF(F11='Lista de Precios'!$E$8,'Lista de Precios'!$E$9,IF(F11='Lista de Precios'!$F$8,'Lista de Precios'!$F$9,IF(F11='Lista de Precios'!$G$8,'Lista de Precios'!$G$9,0)))))*Ingreso!G11 -> 1690
B12: Turno 6 | C12: 0.79166667 | D12: 0.83958333 | E12: Bàsico | F12: Completo | G12: 10 | I12: =D12-C12 -> 0.047916667 | J12: =IF(HOUR(I12)<1,_xlfn.CEILING.MATH(I12,"01:00"),_xlfn.CEILING.MATH(I12,"00:10")) -> 0.048611111 | K12: =((HOUR(J12)*'Lista de Precios'!$C$5)+(MINUTE(J12)/10*'Lista de Precios'!$E$5))*G12 -> 1150 | L12: =IF(C12>0.75, ((HOUR(J12)*'Lista de Precios'!$D$5)+(MINUTE(J12)/10*'Lista de Precios'!$F$5))*G12, 0) -> 95 | N12: =IF(E12='Lista de Precios'!$C$6,'Lista de Precios'!$C$7,IF(E12='Lista de Precios'!$D$6,'Lista de Precios'!$D$7,IF(E12='Lista de Precios'!$E$6,'Lista de Precios'!$E$7,IF(E12='Lista de Precios'!$F$6,'Lista de Precios'!$F$7,0))))*G12 -> 300 | O12: =IF(F12='Lista de Precios'!$C$8,'Lista de Precios'!$C$9,IF(F12='Lista de Precios'!$D$8,'Lista de Precios'!$D$9,IF(F12='Lista de Precios'!$E$8,'Lista de Precios'!$E$9,IF(F12='Lista de Precios'!$F$8,'Lista de Precios'!$F$9,IF(F12='Lista de Precios'!$G$8,'Lista de Precios'!$G$9,0)))))*Ingreso!G12 -> 1850
B13: Turno 7 | C13: 0.875 | D13: 0.9375 | E13: No | F13: No | G13: 14 | I13: =D13-C13 -> 0.0625 | J13: =IF(HOUR(I13)<1,_xlfn.CEILING.MATH(I13,"01:00"),_xlfn.CEILING.MATH(I13,"00:10")) -> 0.0625 | K13: =((HOUR(J13)*'Lista de Precios'!$C$5)+(MINUTE(J13)/10*'Lista de Precios'!$E$5))*G13 -> 2030 | L13: =IF(C13>0.75, ((HOUR(J13)*'Lista de Precios'!$D$5)+(MINUTE(J13)/10*'Lista de Precios'!$F$5))*G13, 0) -> 175 | N13: =IF(E13='Lista de Precios'!$C$6,'Lista de Precios'!$C$7,IF(E13='Lista de Precios'!$D$6,'Lista de Precios'!$D$7,IF(E13='Lista de Precios'!$E$6,'Lista de Precios'!$E$7,IF(E13='Lista de Precios'!$F$6,'Lista de Precios'!$F$7,0))))*G13 -> 0 | O13: =IF(F13='Lista de Precios'!$C$8,'Lista de Precios'!$C$9,IF(F13='Lista de Precios'!$D$8,'Lista de Precios'!$D$9,IF(F13='Lista de Precios'!$E$8,'Lista de Precios'!$E$9,IF(F13='Lista de Precios'!$F$8,'Lista de Precios'!$F$9,IF(F13='Lista de Precios'!$G$8,'Lista de Precios'!$G$9,0)))))*Ingreso!G13 -> 0
J14: =SUM(J7:J13) -> 0.46527778 | K14: =SUM(K7:K13) -> 13715 | L14: =SUM(L7:L13) -> 270 | N14: =SUM(N7:N13) -> 3780 | O14: =SUM(O7:O13) -> 7710
B15: Adicionales Diarios
E18: Observaciones

Sheet Lista de Precios
B2: INGRESOS
B4: Horas Cancha | C4: Diurno | D4: Nocturno | E4: Hora Fracción | F4: lUZ Fracción
C5: 100 | D5: 8 | E5: 15 | F5: 1.5
B6: Vestuario | C6: No | D6: Bàsico | E6: Confort | F6: Premium
C7: 0 | D7: 30 | E7: 60 | F7: 120
B8: Refrigerio | C8: No | D8: Minimo | E8: Bàsico | F8: Abundante | G8: Completo
C9: 0 | D9: 90 | E9: 110 | F9: 130 | G9: 185
B10: Descuentos | C10: 1 a 10 | D10: 11 a 15 | E10: 16 o +
C11: 0 | D11: 10 | E11: 15
B13: COSTOS
B15: Riego de Cancha | C15: 160
B16: Limpieza de Vestuarios | C16: 300
B17: Reparacion de Redes | C17: 100
B18: Inflar Pelotas | C18: 70
B20: Descuentos | C20: Normal | D20: Domingo | E20: Feriado
C21: 1600 | D21: 2200 | E21: 3200

Sheet Resumen
C2: =Ingreso!C2 -> Federico | I2: =Ingreso!C3 -> 44007
C4: =Ingreso!J7 -> 0.0625 | D4: =Ingreso!J8 -> 0.048611111 | E4: =Ingreso!J9 -> 0.041666667 | F4: =Ingreso!J10 -> 0.090277778 | G4: =Ingreso!J11 -> 0.11111111 | H4: =Ingreso!J12 -> 0.048611111 | I4: =Ingreso!J13 -> 0.0625 | K4: =Ingreso!K14 -> 13715
C5: =IF(Ingreso!L7>0,"Si","No") -> No | D5: =IF(Ingreso!L8>0,"Si","No") -> No | E5: =IF(Ingreso!L9>0,"Si","No") -> No | F5: =IF(Ingreso!L10>0,"Si","No") -> No | G5: =IF(Ingreso!L11,"Si","No") -> No | H5: =IF(Ingreso!L12>0,"Si","No") -> Si | I5: =IF(Ingreso!L13>0,"Si","No") -> Si | K5: =Ingreso!L14 -> 270
C6: =IF(Ingreso!E7='Lista de Precios'!$C$6,"N",IF(Ingreso!E7='Lista de Precios'!$D$6,"B",IF(Ingreso!E7='Lista de Precios'!$E$6,"C",IF(Ingreso!E7='Lista de Precios'!$F$6,"P","")))) -> B | D6: =IF(Ingreso!E8='Lista de Precios'!$C$6,"N",IF(Ingreso!E8='Lista de Precios'!$D$6,"B",IF(Ingreso!E8='Lista de Precios'!$E$6,"C",IF(Ingreso!E8='Lista de Precios'!$F$6,"P","")))) -> C | E6: =IF(Ingreso!E9='Lista de Precios'!$C$6,"N",IF(Ingreso!E9='Lista de Precios'!$D$6,"B",IF(Ingreso!E9='Lista de Precios'!$E$6,"C",IF(Ingreso!E9='Lista de Precios'!$F$6,"P","")))) -> N | F6: =IF(Ingreso!E10='Lista de Precios'!$C$6,"N",IF(Ingreso!E10='Lista de Precios'!$D$6,"B",IF(Ingreso!E10='Lista de Precios'!$E$6,"C",IF(Ingreso!E10='Lista de Precios'!$F$6,"P","")))) -> C | G6: =IF(Ingreso!E11='Lista de Precios'!$C$6,"N",IF(Ingreso!E11='Lista de Precios'!$D$6,"B",IF(Ingreso!E11='Lista de Precios'!$E$6,"C",IF(Ingreso!E11='Lista de Precios'!$F$6,"P","")))) -> P | H6: =IF(Ingreso!E12='Lista de Precios'!$C$6,"N",IF(Ingreso!E12='Lista de Precios'!$D$6,"B",IF(Ingreso!E12='Lista de Precios'!$E$6,"C",IF(Ingreso!E12='Lista de Precios'!$F$6,"P","")))) -> B | I6: =IF(Ingreso!E13='Lista de Precios'!$C$6,"N",IF(Ingreso!E13='Lista de Precios'!$D$6,"B",IF(Ingreso!E13='Lista de Precios'!$E$6,"C",IF(Ingreso!E13='Lista de Precios'!$F$6,"P","")))) -> N | K6: =Ingreso!N14 -> 3780
C7: =IF(Ingreso!F7='Lista de Precios'!$C$8,"N",IF(Ingreso!F7='Lista de Precios'!$D$8,"M",IF(Ingreso!F7='Lista de Precios'!$E$8,"B",IF(Ingreso!F7='Lista de Precios'!$F$8,"A",IF(Ingreso!F7='Lista de Precios'!$G$8,"C",""))))) -> M | D7: =IF(Ingreso!F8='Lista de Precios'!$C$8,"N",IF(Ingreso!F8='Lista de Precios'!$D$8,"M",IF(Ingreso!F8='Lista de Precios'!$E$8,"B",IF(Ingreso!F8='Lista de Precios'!$F$8,"A",IF(Ingreso!F8='Lista de Precios'!$G$8,"C",""))))) -> B | E7: =IF(Ingreso!F9='Lista de Precios'!$C$8,"N",IF(Ingreso!F9='Lista de Precios'!$D$8,"M",IF(Ingreso!F9='Lista de Precios'!$E$8,"B",IF(Ingreso!F9='Lista de Precios'!$F$8,"A",IF(Ingreso!F9='Lista de Precios'!$G$8,"C",""))))) -> N | F7: =IF(Ingreso!F10='Lista de Precios'!$C$8,"N",IF(Ingreso!F10='Lista de Precios'!$D$8,"M",IF(Ingreso!F10='Lista de Precios'!$E$8,"B",IF(Ingreso!F10='Lista de Precios'!$F$8,"A",IF(Ingreso!F10='Lista de Precios'!$G$8,"C",""))))) -> A | G7: =IF(Ingreso!F11='Lista de Precios'!$C$8,"N",IF(Ingreso!F11='Lista de Precios'!$D$8,"M",IF(Ingreso!F11='Lista de Precios'!$E$8,"B",IF(Ingreso!F11='Lista de Precios'!$F$8,"A",IF(Ingreso!F11='Lista de Precios'!$G$8,"C",""))))) -> A | H7: =IF(Ingreso!F12='Lista de Precios'!$C$8,"N",IF(Ingreso!F12='Lista de Precios'!$D$8,"M",IF(Ingreso!F12='Lista de Precios'!$E$8,"B",IF(Ingreso!F12='Lista de Precios'!$F$8,"A",IF(Ingreso!F12='Lista de Precios'!$G$8,"C",""))))) -> C | I7: =IF(Ingreso!F13='Lista de Precios'!$C$8,"N",IF(Ingreso!F13='Lista de Precios'!$D$8,"M",IF(Ingreso!F13='Lista de Precios'!$E$8,"B",IF(Ingreso!F13='Lista de Precios'!$F$8,"A",IF(Ingreso!F13='Lista de Precios'!$G$8,"C",""))))) -> N | K7: =Ingreso!O14 -> 7710
